{
    "meta": {
        "0": "alignment",
        "1": "debug",
        "10": "vOffset",
        "2": "firstName",
        "3": "hOffset",
        "4": "name",
        "5": "personDetailsList",
        "6": "cityOfPersonLiving",
        "7": "dateOfBirth",
        "8": "lastName",
        "9": "src"
    },
    "result": {
        "0": "center",
        "1": "on",
        "10": 250,
        "2": "arun",
        "3": 250,
        "4": "sun1",
        "5": [
            {
                "2": "arun",
                "6": "madurai",
                "7": "1989-12-12",
                "8": "raj"
            },
            {
                "2": "kumar",
                "6": "madurai",
                "7": "1989-12-11",
                "8": "raj"
            },
            {
                "2": "arun",
                "6": "madurai",
                "7": "1989-12-10",
                "8": "raj"
            },
            {
                "2": "baskar",
                "6": "madurai",
                "7": "1989-12-09",
                "8": "raj"
            },
            {
                "2": "raja",
                "6": "madurai",
                "7": "1989-12-08",
                "8": "ram"
            },
            {
                "2": "ram",
                "6": "madurai",
                "7": "1989-12-07",
                "8": "kumar"
            },
            {
                "2": "johnson",
                "6": "madurai",
                "7": "1989-12-01",
                "8": "raj"
            },
            {
                "2": "john",
                "6": "madurai",
                "7": "1989-12-02",
                "8": "raj"
            },
            {
                "2": "kumar",
                "6": "madurai",
                "7": "1989-12-16",
                "8": "john"
            },
            {
                "2": "arun",
                "6": "madurai",
                "7": "1989-12-20",
                "8": "raj"
            },
            {
                "2": "kumar",
                "6": "madurai",
                "7": "1989-12-11",
                "8": "raj"
            },
            {
                "2": "kumar",
                "6": "madurai",
                "7": "1989-12-11",
                "8": "raj"
            },
            {
                "2": "kumar",
                "6": "madurai",
                "7": "1989-12-11",
                "8": "raj"
            },
            {
                "2": "kumar",
                "6": "madurai",
                "7": "1989-12-11",
                "8": "raj"
            },
            {
                "2": "kumar",
                "6": "madurai",
                "7": "1989-12-11",
                "8": "raj"
            },
            {
                "2": "kumar",
                "6": "madurai",
                "7": "1989-12-11",
                "8": "raj"
            },
            {
                "2": "kumar",
                "6": "madurai",
                "7": "1989-12-11",
                "8": "raj"
            },
            {
                "2": "kumar",
                "6": "madurai",
                "7": "1989-12-11",
                "8": "raj"
            },
            {
                "2": "kumar",
                "6": "madurai",
                "7": "1989-12-11",
                "8": "raj"
            },
            {
                "2": "kumar",
                "6": "madurai",
                "7": "1989-12-11",
                "8": "raj"
            },
            {
                "2": "kumar",
                "6": "madurai",
                "7": "1989-12-11",
                "8": "raj"
            },
            {
                "2": "kumar",
                "6": "madurai",
                "7": "1989-12-11",
                "8": "raj"
            },
            {
                "2": "kumar",
                "6": "madurai",
                "7": "1989-12-11",
                "8": "raj"
            },
            {
                "2": "kumar",
                "6": "madurai",
                "7": "1989-12-11",
                "8": "raj"
            },
            {
                "2": "kumar",
                "6": "madurai",
                "7": "1989-12-11",
                "8": "raj"
            },
            {
                "2": "kumar",
                "6": "madurai",
                "7": "1989-12-11",
                "8": "raj"
            },
            {
                "2": "kumar",
                "6": "madurai",
                "7": "1989-12-11",
                "8": "raj"
            },
            {
                "2": "kumar",
                "6": "madurai",
                "7": "1989-12-11",
                "8": "raj"
            },
            {
                "2": "kumar",
                "6": "madurai",
                "7": "1989-12-11",
                "8": "raj"
            },
            {
                "2": "kumar",
                "6": "madurai",
                "7": "1989-12-11",
                "8": "raj"
            },
            {
                "2": "kumar",
                "6": "madurai",
                "7": "1989-12-11",
                "8": "raj"
            },
            {
                "2": "kumar",
                "6": "madurai",
                "7": "1989-12-11",
                "8": "raj"
            },
            {
                "2": "kumar",
                "6": "madurai",
                "7": "1989-12-11",
                "8": "raj"
            },
            {
                "2": "kumar",
                "6": "madurai",
                "7": "1989-12-11",
                "8": "raj"
            },
            {
                "2": "kumar",
                "6": "madurai",
                "7": "1989-12-11",
                "8": "raj"
            },
            {
                "2": "kumar",
                "6": "madurai",
                "7": "1989-12-11",
                "8": "raj"
            },
            {
                "2": "kumar",
                "6": "madurai",
                "7": "1989-12-11",
                "8": "raj"
            },
            {
                "2": "kumar",
                "6": "madurai",
                "7": "1989-12-11",
                "8": "raj"
            },
            {
                "2": "kumar",
                "6": "madurai",
                "7": "1989-12-11",
                "8": "raj"
            },
            {
                "2": "kumar",
                "6": "madurai",
                "7": "1989-12-11",
                "8": "raj"
            }
        ],
        "9": "Images/Sun.png"
    }
}